odoo/addons/sale_mail_autosubscribe/README.rst
odoo/addons/sale_mail_autosubscribe/__init__.py
odoo/addons/sale_mail_autosubscribe/__manifest__.py
odoo/addons/sale_mail_autosubscribe/data/mail_autosubscribe.xml
odoo/addons/sale_mail_autosubscribe/i18n/it.po
odoo/addons/sale_mail_autosubscribe/i18n/sale_mail_autosubscribe.pot
odoo/addons/sale_mail_autosubscribe/readme/CONFIGURE.md
odoo/addons/sale_mail_autosubscribe/readme/CONTRIBUTORS.md
odoo/addons/sale_mail_autosubscribe/readme/DESCRIPTION.md
odoo/addons/sale_mail_autosubscribe/static/description/icon.png
odoo/addons/sale_mail_autosubscribe/static/description/index.html
odoo_addon_sale_mail_autosubscribe-18.0.1.0.0.2.dist-info/METADATA
odoo_addon_sale_mail_autosubscribe-18.0.1.0.0.2.dist-info/WHEEL
odoo_addon_sale_mail_autosubscribe-18.0.1.0.0.2.dist-info/top_level.txt
odoo_addon_sale_mail_autosubscribe-18.0.1.0.0.2.dist-info/RECORD
